pyhgvs/__init__.py
pyhgvs/models.py
pyhgvs/utils.py
pyhgvs/variants.py
pyhgvs/tests/__init__.py
pyhgvs/tests/genome.py
pyhgvs/tests/test_hgvs_names.py
pyhgvs/tests/test_hgvs_names_long.py
pyhgvs/tests/test_variants.py
pyhgvs-0.11.1.dist-info/LICENSE
pyhgvs-0.11.1.dist-info/METADATA
pyhgvs-0.11.1.dist-info/WHEEL
pyhgvs-0.11.1.dist-info/top_level.txt
pyhgvs-0.11.1.dist-info/RECORD
