Metadata-Version: 2.1
Name: pyhgvs
Version: 0.11.1
Summary: HGVS name parsing and formatting
Home-page: UNKNOWN
Author: Matt Rasmussen
Author-email: rasmus@counsyl.com
License: UNKNOWN
Platform: UNKNOWN
Requires-Dist: pip (>=1.2)
